md_planning/__init__.py
md_planning/cli.py
md_planning/md_planning.py
md_planning-0.5.0.dist-info/AUTHORS.rst
md_planning-0.5.0.dist-info/LICENSE
md_planning-0.5.0.dist-info/METADATA
md_planning-0.5.0.dist-info/WHEEL
md_planning-0.5.0.dist-info/entry_points.txt
md_planning-0.5.0.dist-info/top_level.txt
md_planning-0.5.0.dist-info/RECORD
