Metadata-Version: 2.1
Name: md-planning
Version: 0.5.0
Summary: package to define, visualize with gantt and budget projects using yaml syntax. 
Home-page: https://github.com/mtllr/md_planning
Author: Martin Teller
Author-email: martintellerpro@gmail.com
License: MIT license
Project-URL: Homepage, https://github.com/mtllr/md_planning
Project-URL: Documentation, https://md-planning.readthedocs.io
Project-URL: Buy me a coffee, https://www.buymeacoffee.com/mtllr
Keywords: md_planning project gantt PERT CPM budgeting budget visualization
Classifier: Development Status :: 2 - Pre-Alpha
Classifier: Intended Audience :: Developers
Classifier: License :: OSI Approved :: MIT License
Classifier: Natural Language :: English
Classifier: Programming Language :: Python :: 3
Classifier: Programming Language :: Python :: 3.7
Classifier: Programming Language :: Python :: 3.8
Classifier: Programming Language :: Python :: 3.9
Classifier: Programming Language :: Python :: 3.10
Requires-Python: >=3.7
License-File: LICENSE
License-File: AUTHORS.rst
Requires-Dist: Click (>=7.0)
Requires-Dist: pyyaml (==6.0)
Requires-Dist: python-gantt (==0.6.0)
Requires-Dist: python-gantt-csv (==0.4.0)
Requires-Dist: pertchart (==0.5.1)
Requires-Dist: criticalpath (==0.1.5)
Requires-Dist: networkx (==2.8.4)
Requires-Dist: pint (==0.19.2)
Requires-Dist: pandas (==1.4.3)
Requires-Dist: tabulate (==0.8.10)
Requires-Dist: matplotlib (==3.6.0)
